numerical_pde_solver/__init__.py
numerical_pde_solver/euler.py
numerical_pde_solver/milstein.py
tests/__init__.py
tests/test_euler.py
tests/test_milstein.py
numerical_pde_solver-0.1.4.dist-info/METADATA
numerical_pde_solver-0.1.4.dist-info/WHEEL
numerical_pde_solver-0.1.4.dist-info/top_level.txt
numerical_pde_solver-0.1.4.dist-info/RECORD
