Metadata-Version: 2.1
Name: numerical-pde-solver
Version: 0.1.4
Summary: A small package for solving PDEs using numerical methods
Home-page: https://github.com/AIM-IT4/numerical-pde-solver
Author: Amit Kumar Jha
Author-email: jha.8@alumni.iitj.ac.in
Project-URL: Bug Tracker, https://github.com/AIM-IT4/numerical-pde-solver/issues
Classifier: Programming Language :: Python :: 3
Classifier: License :: OSI Approved :: MIT License
Classifier: Operating System :: OS Independent
Requires-Python: >=3.6
Requires-Dist: numpy
